{"id":"c58d7a66-c88c-4f45-9142-d1bf12e5d76a","enabled":true,"name":"Phoenix's Modified Upper Body Rotation 0.1.0","panningX":1874.35156,"panningY":344.111084,"scaling":0.340730578,"nodes":{"5bbb8b57-9d79-465e-9e94-6be043e5f9fb":{"id":"5bbb8b57-9d79-465e-9e94-6be043e5f9fb","dataInputs":{"Vector3":{"type":"UnityEngine.Vector3","value":"{\"x\":0.0,\"y\":0.3,\"z\":0.0}"},"Scale":{"type":"UnityEngine.Vector3","value":"{\"x\":0.362640381,\"y\":-0.461547852,\"z\":0.0}"}},"typeId":"31575577-e750-4abc-98ae-dd8129505046","name":"VECTOR3_SCALE_VECTOR3","x":657.3005,"y":311.0445},"4ff5a3d9-fab4-4460-82e5-d10fa4309a29":{"id":"4ff5a3d9-fab4-4460-82e5-d10fa4309a29","dataInputs":{"Character":{"type":"Warudo.Plugins.Core.Assets.Character.CharacterAsset","value":"{\"id\":\"29399e49-1c26-41bb-b40f-294dc0590f68\",\"name\":\"Character\"}"},"BoneRotationOffsets":{"type":"UnityEngine.Quaternion[]","value":"[{\"x\":0.0,\"y\":-0.00120832911,\"z\":0.0,\"w\":0.9999993},{\"x\":0.0,\"y\":0.0,\"z\":0.0,\"w\":1.0},{\"x\":0.0,\"y\":0.0,\"z\":0.0,\"w\":1.0},{\"x\":0.0,\"y\":0.0,\"z\":0.0,\"w\":1.0},{\"x\":0.0,\"y\":0.0,\"z\":0.0,\"w\":1.0},{\"x\":0.0,\"y\":0.0,\"z\":0.0,\"w\":1.0},{\"x\":0.0,\"y\":0.0,\"z\":0.0,\"w\":1.0},{\"x\":0.0,\"y\":-0.00161110528,\"z\":0.0,\"w\":0.9999987},{\"x\":0.0,\"y\":-0.00241665659,\"z\":0.0,\"w\":0.9999971},{\"x\":0.0,\"y\":0.0,\"z\":0.0,\"w\":1.0},{\"x\":0.0,\"y\":0.0,\"z\":0.0,\"w\":1.0},{\"x\":0.0,\"y\":0.0,\"z\":-0.0295992289,\"w\":0.999561846},{\"x\":0.0,\"y\":0.0,\"z\":0.0295992289,\"w\":0.999561846},{\"x\":0.0,\"y\":0.0,\"z\":-0.05917252,\"w\":0.998247743},{\"x\":0.0,\"y\":0.0,\"z\":0.05917252,\"w\":0.998247743},{\"x\":0.0,\"y\":0.0,\"z\":-0.05917252,\"w\":0.998247743},{\"x\":0.0,\"y\":0.0,\"z\":0.05917252,\"w\":0.998247743},{\"x\":0.0,\"y\":0.0,\"z\":-0.23462075,\"w\":0.972086966},{\"x\":0.0,\"y\":0.0,\"z\":0.23462075,\"w\":0.972086966},{\"x\":0.0,\"y\":0.0,\"z\":0.0,\"w\":1.0},{\"x\":0.0,\"y\":0.0,\"z\":0.0,\"w\":1.0},{\"x\":0.0,\"y\":0.0,\"z\":0.0,\"w\":1.0},{\"x\":0.0,\"y\":0.0,\"z\":0.0,\"w\":1.0},{\"x\":0.0,\"y\":0.0,\"z\":0.0,\"w\":1.0},{\"x\":0.0,\"y\":0.0,\"z\":0.0,\"w\":1.0},{\"x\":0.0,\"y\":0.0,\"z\":0.0,\"w\":1.0},{\"x\":0.0,\"y\":0.0,\"z\":0.0,\"w\":1.0},{\"x\":0.0,\"y\":0.0,\"z\":0.0,\"w\":1.0},{\"x\":0.0,\"y\":0.0,\"z\":0.0,\"w\":1.0},{\"x\":0.0,\"y\":0.0,\"z\":0.0,\"w\":1.0},{\"x\":0.0,\"y\":0.0,\"z\":0.0,\"w\":1.0},{\"x\":0.0,\"y\":0.0,\"z\":0.0,\"w\":1.0},{\"x\":0.0,\"y\":0.0,\"z\":0.0,\"w\":1.0},{\"x\":0.0,\"y\":0.0,\"z\":0.0,\"w\":1.0},{\"x\":0.0,\"y\":0.0,\"z\":0.0,\"w\":1.0},{\"x\":0.0,\"y\":0.0,\"z\":0.0,\"w\":1.0},{\"x\":0.0,\"y\":0.0,\"z\":0.0,\"w\":1.0},{\"x\":0.0,\"y\":0.0,\"z\":0.0,\"w\":1.0},{\"x\":0.0,\"y\":0.0,\"z\":0.0,\"w\":1.0},{\"x\":0.0,\"y\":0.0,\"z\":0.0,\"w\":1.0},{\"x\":0.0,\"y\":0.0,\"z\":0.0,\"w\":1.0},{\"x\":0.0,\"y\":0.0,\"z\":0.0,\"w\":1.0},{\"x\":0.0,\"y\":0.0,\"z\":0.0,\"w\":1.0},{\"x\":0.0,\"y\":0.0,\"z\":0.0,\"w\":1.0},{\"x\":0.0,\"y\":0.0,\"z\":0.0,\"w\":1.0},{\"x\":0.0,\"y\":0.0,\"z\":0.0,\"w\":1.0},{\"x\":0.0,\"y\":0.0,\"z\":0.0,\"w\":1.0},{\"x\":0.0,\"y\":0.0,\"z\":0.0,\"w\":1.0},{\"x\":0.0,\"y\":0.0,\"z\":0.0,\"w\":1.0},{\"x\":0.0,\"y\":0.0,\"z\":0.0,\"w\":1.0},{\"x\":0.0,\"y\":0.0,\"z\":0.0,\"w\":1.0},{\"x\":0.0,\"y\":0.0,\"z\":0.0,\"w\":1.0},{\"x\":0.0,\"y\":0.0,\"z\":0.0,\"w\":1.0},{\"x\":0.0,\"y\":0.0,\"z\":0.0,\"w\":1.0},{\"x\":0.0,\"y\":0.0,\"z\":0.0,\"w\":1.0}]"},"Immediate":{"type":"bool","value":"false"}},"typeId":"ba9f4c5c-147f-4f40-85b8-b60757e3bbaa","name":"OVERRIDE_CHARACTER_BONE_ROTATION_OFFSETS","x":1229.47388,"y":-465.406647},"6728c52d-c7b2-4848-b5aa-1c3a5209b65e":{"id":"6728c52d-c7b2-4848-b5aa-1c3a5209b65e","dataInputs":{"Rotations":{"type":"UnityEngine.Quaternion[]","value":"[{\"x\":0.0,\"y\":0.0,\"z\":0.0,\"w\":1.0},{\"x\":0.0,\"y\":0.0,\"z\":0.0,\"w\":1.0},{\"x\":0.0,\"y\":0.0,\"z\":0.0,\"w\":1.0},{\"x\":0.0,\"y\":0.0,\"z\":0.0,\"w\":1.0},{\"x\":0.0,\"y\":0.0,\"z\":0.0,\"w\":1.0},{\"x\":0.0,\"y\":0.0,\"z\":0.0,\"w\":1.0},{\"x\":0.0,\"y\":0.0,\"z\":0.0,\"w\":1.0},{\"x\":0.0,\"y\":0.0,\"z\":0.0,\"w\":1.0},{\"x\":0.0,\"y\":-0.00241665659,\"z\":0.0,\"w\":0.9999971},{\"x\":0.0,\"y\":0.0,\"z\":0.0,\"w\":1.0},{\"x\":0.0,\"y\":0.0,\"z\":0.0,\"w\":1.0},{\"x\":0.0,\"y\":0.0,\"z\":-0.0295992289,\"w\":0.999561846},{\"x\":0.0,\"y\":0.0,\"z\":0.0295992289,\"w\":0.999561846},{\"x\":0.0,\"y\":0.0,\"z\":-0.05917252,\"w\":0.998247743},{\"x\":0.0,\"y\":0.0,\"z\":0.05917252,\"w\":0.998247743},{\"x\":0.0,\"y\":0.0,\"z\":-0.05917252,\"w\":0.998247743},{\"x\":0.0,\"y\":0.0,\"z\":0.05917252,\"w\":0.998247743},{\"x\":0.0,\"y\":0.0,\"z\":-0.23462075,\"w\":0.972086966},{\"x\":0.0,\"y\":0.0,\"z\":0.23462075,\"w\":0.972086966},{\"x\":0.0,\"y\":0.0,\"z\":0.0,\"w\":1.0},{\"x\":0.0,\"y\":0.0,\"z\":0.0,\"w\":1.0},{\"x\":0.0,\"y\":0.0,\"z\":0.0,\"w\":1.0},{\"x\":0.0,\"y\":0.0,\"z\":0.0,\"w\":1.0},{\"x\":0.0,\"y\":0.0,\"z\":0.0,\"w\":1.0},{\"x\":0.0,\"y\":0.0,\"z\":0.0,\"w\":1.0},{\"x\":0.0,\"y\":0.0,\"z\":0.0,\"w\":1.0},{\"x\":0.0,\"y\":0.0,\"z\":0.0,\"w\":1.0},{\"x\":0.0,\"y\":0.0,\"z\":0.0,\"w\":1.0},{\"x\":0.0,\"y\":0.0,\"z\":0.0,\"w\":1.0},{\"x\":0.0,\"y\":0.0,\"z\":0.0,\"w\":1.0},{\"x\":0.0,\"y\":0.0,\"z\":0.0,\"w\":1.0},{\"x\":0.0,\"y\":0.0,\"z\":0.0,\"w\":1.0},{\"x\":0.0,\"y\":0.0,\"z\":0.0,\"w\":1.0},{\"x\":0.0,\"y\":0.0,\"z\":0.0,\"w\":1.0},{\"x\":0.0,\"y\":0.0,\"z\":0.0,\"w\":1.0},{\"x\":0.0,\"y\":0.0,\"z\":0.0,\"w\":1.0},{\"x\":0.0,\"y\":0.0,\"z\":0.0,\"w\":1.0},{\"x\":0.0,\"y\":0.0,\"z\":0.0,\"w\":1.0},{\"x\":0.0,\"y\":0.0,\"z\":0.0,\"w\":1.0},{\"x\":0.0,\"y\":0.0,\"z\":0.0,\"w\":1.0},{\"x\":0.0,\"y\":0.0,\"z\":0.0,\"w\":1.0},{\"x\":0.0,\"y\":0.0,\"z\":0.0,\"w\":1.0},{\"x\":0.0,\"y\":0.0,\"z\":0.0,\"w\":1.0},{\"x\":0.0,\"y\":0.0,\"z\":0.0,\"w\":1.0},{\"x\":0.0,\"y\":0.0,\"z\":0.0,\"w\":1.0},{\"x\":0.0,\"y\":0.0,\"z\":0.0,\"w\":1.0},{\"x\":0.0,\"y\":0.0,\"z\":0.0,\"w\":1.0},{\"x\":0.0,\"y\":0.0,\"z\":0.0,\"w\":1.0},{\"x\":0.0,\"y\":0.0,\"z\":0.0,\"w\":1.0},{\"x\":0.0,\"y\":0.0,\"z\":0.0,\"w\":1.0},{\"x\":0.0,\"y\":0.0,\"z\":0.0,\"w\":1.0},{\"x\":0.0,\"y\":0.0,\"z\":0.0,\"w\":1.0},{\"x\":0.0,\"y\":0.0,\"z\":0.0,\"w\":1.0},{\"x\":0.0,\"y\":0.0,\"z\":0.0,\"w\":1.0},{\"x\":0.0,\"y\":0.0,\"z\":0.0,\"w\":1.0}]"},"Bones":{"type":"UnityEngine.HumanBodyBones[]","value":"[{\"label\":\"Spine\",\"value\":7,\"description\":null,\"icon\":null}]"},"OffsetEulerAngle":{"type":"UnityEngine.Vector3","value":"{\"x\":0.0,\"y\":-0.184619144,\"z\":0.0}"}},"typeId":"72905b4e-4efa-41b3-a014-7468b77515bb","name":"OFFSET_CHARACTER_BONE_ROTATIONS","x":603.267151,"y":-165.572},"2d7d151c-cdf9-46d0-b0ae-6826e617542f":{"id":"2d7d151c-cdf9-46d0-b0ae-6826e617542f","dataInputs":{},"typeId":"e4140b42-efde-491a-ad88-21038f0289e2","name":"ON_UPDATE","x":435.760773,"y":-491.924622},"58321c17-cd8e-4868-8f19-da8f940ca059":{"id":"58321c17-cd8e-4868-8f19-da8f940ca059","dataInputs":{"Vector3":{"type":"UnityEngine.Vector3","value":"{\"x\":0.0,\"y\":0.6,\"z\":0.0}"},"Scale":{"type":"UnityEngine.Vector3","value":"{\"x\":0.362640381,\"y\":-0.461547852,\"z\":0.0}"}},"typeId":"31575577-e750-4abc-98ae-dd8129505046","name":"VECTOR3_SCALE_VECTOR3","x":-60.5066,"y":310.643433},"26500fe5-1342-46b9-b3ac-200daaa34bdf":{"id":"26500fe5-1342-46b9-b3ac-200daaa34bdf","dataInputs":{"Rotations":{"type":"UnityEngine.Quaternion[]","value":"[{\"x\":0.0,\"y\":0.0,\"z\":0.0,\"w\":1.0},{\"x\":0.0,\"y\":0.0,\"z\":0.0,\"w\":1.0},{\"x\":0.0,\"y\":0.0,\"z\":0.0,\"w\":1.0},{\"x\":0.0,\"y\":0.0,\"z\":0.0,\"w\":1.0},{\"x\":0.0,\"y\":0.0,\"z\":0.0,\"w\":1.0},{\"x\":0.0,\"y\":0.0,\"z\":0.0,\"w\":1.0},{\"x\":0.0,\"y\":0.0,\"z\":0.0,\"w\":1.0},{\"x\":0.0,\"y\":-0.00161110528,\"z\":0.0,\"w\":0.9999987},{\"x\":0.0,\"y\":-0.00241665659,\"z\":0.0,\"w\":0.9999971},{\"x\":0.0,\"y\":0.0,\"z\":0.0,\"w\":1.0},{\"x\":0.0,\"y\":0.0,\"z\":0.0,\"w\":1.0},{\"x\":0.0,\"y\":0.0,\"z\":-0.0295992289,\"w\":0.999561846},{\"x\":0.0,\"y\":0.0,\"z\":0.0295992289,\"w\":0.999561846},{\"x\":0.0,\"y\":0.0,\"z\":-0.05917252,\"w\":0.998247743},{\"x\":0.0,\"y\":0.0,\"z\":0.05917252,\"w\":0.998247743},{\"x\":0.0,\"y\":0.0,\"z\":-0.05917252,\"w\":0.998247743},{\"x\":0.0,\"y\":0.0,\"z\":0.05917252,\"w\":0.998247743},{\"x\":0.0,\"y\":0.0,\"z\":-0.23462075,\"w\":0.972086966},{\"x\":0.0,\"y\":0.0,\"z\":0.23462075,\"w\":0.972086966},{\"x\":0.0,\"y\":0.0,\"z\":0.0,\"w\":1.0},{\"x\":0.0,\"y\":0.0,\"z\":0.0,\"w\":1.0},{\"x\":0.0,\"y\":0.0,\"z\":0.0,\"w\":1.0},{\"x\":0.0,\"y\":0.0,\"z\":0.0,\"w\":1.0},{\"x\":0.0,\"y\":0.0,\"z\":0.0,\"w\":1.0},{\"x\":0.0,\"y\":0.0,\"z\":0.0,\"w\":1.0},{\"x\":0.0,\"y\":0.0,\"z\":0.0,\"w\":1.0},{\"x\":0.0,\"y\":0.0,\"z\":0.0,\"w\":1.0},{\"x\":0.0,\"y\":0.0,\"z\":0.0,\"w\":1.0},{\"x\":0.0,\"y\":0.0,\"z\":0.0,\"w\":1.0},{\"x\":0.0,\"y\":0.0,\"z\":0.0,\"w\":1.0},{\"x\":0.0,\"y\":0.0,\"z\":0.0,\"w\":1.0},{\"x\":0.0,\"y\":0.0,\"z\":0.0,\"w\":1.0},{\"x\":0.0,\"y\":0.0,\"z\":0.0,\"w\":1.0},{\"x\":0.0,\"y\":0.0,\"z\":0.0,\"w\":1.0},{\"x\":0.0,\"y\":0.0,\"z\":0.0,\"w\":1.0},{\"x\":0.0,\"y\":0.0,\"z\":0.0,\"w\":1.0},{\"x\":0.0,\"y\":0.0,\"z\":0.0,\"w\":1.0},{\"x\":0.0,\"y\":0.0,\"z\":0.0,\"w\":1.0},{\"x\":0.0,\"y\":0.0,\"z\":0.0,\"w\":1.0},{\"x\":0.0,\"y\":0.0,\"z\":0.0,\"w\":1.0},{\"x\":0.0,\"y\":0.0,\"z\":0.0,\"w\":1.0},{\"x\":0.0,\"y\":0.0,\"z\":0.0,\"w\":1.0},{\"x\":0.0,\"y\":0.0,\"z\":0.0,\"w\":1.0},{\"x\":0.0,\"y\":0.0,\"z\":0.0,\"w\":1.0},{\"x\":0.0,\"y\":0.0,\"z\":0.0,\"w\":1.0},{\"x\":0.0,\"y\":0.0,\"z\":0.0,\"w\":1.0},{\"x\":0.0,\"y\":0.0,\"z\":0.0,\"w\":1.0},{\"x\":0.0,\"y\":0.0,\"z\":0.0,\"w\":1.0},{\"x\":0.0,\"y\":0.0,\"z\":0.0,\"w\":1.0},{\"x\":0.0,\"y\":0.0,\"z\":0.0,\"w\":1.0},{\"x\":0.0,\"y\":0.0,\"z\":0.0,\"w\":1.0},{\"x\":0.0,\"y\":0.0,\"z\":0.0,\"w\":1.0},{\"x\":0.0,\"y\":0.0,\"z\":0.0,\"w\":1.0},{\"x\":0.0,\"y\":0.0,\"z\":0.0,\"w\":1.0},{\"x\":0.0,\"y\":0.0,\"z\":0.0,\"w\":1.0}]"},"Bones":{"type":"UnityEngine.HumanBodyBones[]","value":"[{\"label\":\"Hips\",\"value\":0,\"description\":null,\"icon\":null}]"},"OffsetEulerAngle":{"type":"UnityEngine.Vector3","value":"{\"x\":0.0,\"y\":-0.138464361,\"z\":0.0}"}},"typeId":"72905b4e-4efa-41b3-a014-7468b77515bb","name":"OFFSET_CHARACTER_BONE_ROTATIONS","x":935.8127,"y":-164.46814},"eea1cbc8-f7f6-49be-8ecf-127db682d90b":{"id":"eea1cbc8-f7f6-49be-8ecf-127db682d90b","dataInputs":{"Rotations":{"type":"UnityEngine.Quaternion[]","value":"[{\"x\":0.0,\"y\":-0.00120832911,\"z\":0.0,\"w\":0.9999993},{\"x\":0.0,\"y\":0.0,\"z\":-0.00484812632,\"w\":0.999988258},{\"x\":1.44999811E-11,\"y\":2.99081959E-09,\"z\":0.0048481063,\"w\":0.999988258},{\"x\":0.0,\"y\":0.0,\"z\":-0.0174524374,\"w\":0.9998477},{\"x\":0.0,\"y\":0.0,\"z\":0.0174523667,\"w\":0.9998477},{\"x\":0.0,\"y\":0.0,\"z\":0.0,\"w\":1.0},{\"x\":0.0,\"y\":0.0,\"z\":0.0,\"w\":1.0},{\"x\":-0.002653752,\"y\":0.00161113881,\"z\":-4.252692E-06,\"w\":-0.9999952},{\"x\":-0.00132687506,\"y\":0.00241651875,\"z\":-3.1988E-06,\"w\":-0.9999962},{\"x\":0.0,\"y\":0.0,\"z\":0.0,\"w\":1.0},{\"x\":0.0,\"y\":0.0,\"z\":0.0,\"w\":1.0},{\"x\":0.0,\"y\":0.0,\"z\":-0.0295992289,\"w\":0.999561846},{\"x\":0.0,\"y\":0.0,\"z\":0.0295992289,\"w\":0.999561846},{\"x\":0.0,\"y\":0.0,\"z\":-0.05917252,\"w\":0.998247743},{\"x\":0.0,\"y\":0.0,\"z\":0.05917252,\"w\":0.998247743},{\"x\":0.0,\"y\":0.0,\"z\":-0.05917252,\"w\":0.998247743},{\"x\":0.0,\"y\":0.0,\"z\":0.05917252,\"w\":0.998247743},{\"x\":0.0,\"y\":0.0,\"z\":-0.23462075,\"w\":0.972086966},{\"x\":0.0,\"y\":0.0,\"z\":0.23462075,\"w\":0.972086966},{\"x\":0.0,\"y\":0.0,\"z\":0.0,\"w\":1.0},{\"x\":0.0,\"y\":0.0,\"z\":0.0,\"w\":1.0},{\"x\":0.0,\"y\":0.0,\"z\":0.0,\"w\":1.0},{\"x\":0.0,\"y\":0.0,\"z\":0.0,\"w\":1.0},{\"x\":0.0,\"y\":0.0,\"z\":0.0,\"w\":1.0},{\"x\":0.0,\"y\":0.0,\"z\":0.0,\"w\":1.0},{\"x\":0.0,\"y\":0.0,\"z\":0.0,\"w\":1.0},{\"x\":0.0,\"y\":0.0,\"z\":0.0,\"w\":1.0},{\"x\":0.0,\"y\":0.0,\"z\":0.0,\"w\":1.0},{\"x\":0.0,\"y\":0.0,\"z\":0.0,\"w\":1.0},{\"x\":0.0,\"y\":0.0,\"z\":0.0,\"w\":1.0},{\"x\":0.0,\"y\":0.0,\"z\":0.0,\"w\":1.0},{\"x\":0.0,\"y\":0.0,\"z\":0.0,\"w\":1.0},{\"x\":0.0,\"y\":0.0,\"z\":0.0,\"w\":1.0},{\"x\":0.0,\"y\":0.0,\"z\":0.0,\"w\":1.0},{\"x\":0.0,\"y\":0.0,\"z\":0.0,\"w\":1.0},{\"x\":0.0,\"y\":0.0,\"z\":0.0,\"w\":1.0},{\"x\":0.0,\"y\":0.0,\"z\":0.0,\"w\":1.0},{\"x\":0.0,\"y\":0.0,\"z\":0.0,\"w\":1.0},{\"x\":0.0,\"y\":0.0,\"z\":0.0,\"w\":1.0},{\"x\":0.0,\"y\":0.0,\"z\":0.0,\"w\":1.0},{\"x\":0.0,\"y\":0.0,\"z\":0.0,\"w\":1.0},{\"x\":0.0,\"y\":0.0,\"z\":0.0,\"w\":1.0},{\"x\":0.0,\"y\":0.0,\"z\":0.0,\"w\":1.0},{\"x\":0.0,\"y\":0.0,\"z\":0.0,\"w\":1.0},{\"x\":0.0,\"y\":0.0,\"z\":0.0,\"w\":1.0},{\"x\":0.0,\"y\":0.0,\"z\":0.0,\"w\":1.0},{\"x\":0.0,\"y\":0.0,\"z\":0.0,\"w\":1.0},{\"x\":0.0,\"y\":0.0,\"z\":0.0,\"w\":1.0},{\"x\":0.0,\"y\":0.0,\"z\":0.0,\"w\":1.0},{\"x\":0.0,\"y\":0.0,\"z\":0.0,\"w\":1.0},{\"x\":0.0,\"y\":0.0,\"z\":0.0,\"w\":1.0},{\"x\":0.0,\"y\":0.0,\"z\":0.0,\"w\":1.0},{\"x\":0.0,\"y\":0.0,\"z\":0.0,\"w\":1.0},{\"x\":0.0,\"y\":0.0,\"z\":0.0,\"w\":1.0},{\"x\":0.0,\"y\":0.0,\"z\":0.0,\"w\":1.0}]"},"Bones":{"type":"UnityEngine.HumanBodyBones[]","value":"[{\"label\":\"Chest\",\"value\":8,\"description\":null,\"icon\":null}]"},"OffsetEulerAngle":{"type":"UnityEngine.Vector3","value":"{\"x\":0.0,\"y\":-0.276928723,\"z\":0.0}"}},"typeId":"72905b4e-4efa-41b3-a014-7468b77515bb","name":"OFFSET_CHARACTER_BONE_ROTATIONS","x":298.200317,"y":-163.66832},"372dcb2a-01ce-4d69-ba7a-365187c62217":{"id":"372dcb2a-01ce-4d69-ba7a-365187c62217","dataInputs":{"Character":{"type":"Warudo.Plugins.Core.Assets.Character.CharacterAsset","value":"{\"id\":\"29399e49-1c26-41bb-b40f-294dc0590f68\",\"name\":\"Character\"}"}},"typeId":"4b4154ce-7332-4e28-90af-b3dbd04bd2f4","name":"GET_CHARACTER_ANIMATION_PIPELINE_DATA","x":-59.7350922,"y":-357.3865},"7be9914f-70cf-4450-b15c-5d75658ae714":{"id":"7be9914f-70cf-4450-b15c-5d75658ae714","dataInputs":{"Vector3":{"type":"UnityEngine.Vector3","value":"{\"x\":0.0,\"y\":0.4,\"z\":0.0}"},"Scale":{"type":"UnityEngine.Vector3","value":"{\"x\":0.362640381,\"y\":-0.461547852,\"z\":0.0}"}},"typeId":"31575577-e750-4abc-98ae-dd8129505046","name":"VECTOR3_SCALE_VECTOR3","x":300.439026,"y":310.215546},"717cb3d7-58f2-4af2-ab6c-1fccb6b39585":{"id":"717cb3d7-58f2-4af2-ab6c-1fccb6b39585","dataInputs":{"Character":{"type":"Warudo.Plugins.Core.Assets.Character.CharacterAsset","value":"{\"id\":\"29399e49-1c26-41bb-b40f-294dc0590f68\",\"name\":\"Character\"}"},"Bone":{"type":"UnityEngine.HumanBodyBones","value":"{\"label\":\"Head\",\"value\":10,\"description\":null,\"icon\":null}"},"Type":{"type":"Warudo.Plugins.Core.Nodes.GetCharacterBoneRotationNode+BoneRotationType","value":"{\"label\":\"Local Rotation\",\"value\":1,\"description\":null,\"icon\":null}"}},"typeId":"4d31482c-1d4d-42e0-85e8-7cc4a115495e","name":"GET_CHARACTER_BONE_ROTATION","x":-396.7209,"y":656.439148},"669f0adc-879d-45ed-bfcc-d254e1103e33":{"id":"669f0adc-879d-45ed-bfcc-d254e1103e33","dataInputs":{"Text":{"type":"string","value":"\"# README\\n\\nThis blueprint rotates your character's hips, spine and chest based on head rotation, so that your upper body movements look more natural.\\n\\n### Reminders\\n\\n**1.** If you have the \\\"Look At\\\" feature enabled in your face tracking, you may see the character \\\"bounces\\\" their head back to the camera after you rotate your head. If this is undesired, please disable \\\"Look At\\\" in your face tracking.\\n\\n**2.** When your face tracking blueprint is disabled, this blueprint **must also be disabled**. Otherwise... well try it out yourself ;)\""},"Content":{"type":"string","value":"\"# README\\n\\nThis blueprint rotates your character's hips, spine and chest based on head rotation, so that your upper body movements look more natural.\\n\\n### Reminders\\n\\n**1.** If you have the \\\"Look At\\\" feature enabled in your face tracking, you may see the character \\\"bounces\\\" their head back to the camera after you rotate your head. If this is undesired, please disable \\\"Look At\\\" in your face tracking.\\n\\n**2.** When your face tracking blueprint is disabled, this blueprint **must also be disabled**. Otherwise... well try it out yourself ;)\""},"Editing":{"type":"bool","value":"false"}},"typeId":"200ee639-79bc-492c-a14c-a6b64cfcf39d","name":"COMMENT","x":-399.000854,"y":-353.714661},"3adac197-fb55-45c5-a111-12759ea4ceec":{"id":"3adac197-fb55-45c5-a111-12759ea4ceec","dataInputs":{"Text":{"type":"string","value":"\"↑↑↑↑↑↑↑↑\\n\\nChange the Y value to adjust how much the **chest** should rotate based on head rotation.\""},"Content":{"type":"string","value":"\"↑↑↑↑↑↑↑↑\\n\\nChange the Y value to adjust how much the **chest** should rotate based on head rotation.\""},"Editing":{"type":"bool","value":"false"}},"typeId":"200ee639-79bc-492c-a14c-a6b64cfcf39d","name":"COMMENT","x":-62.19154,"y":636.8306},"f52a95ff-608b-4301-98cd-599a250b36c5":{"id":"f52a95ff-608b-4301-98cd-599a250b36c5","dataInputs":{"Text":{"type":"string","value":"\"↑↑↑↑↑↑↑↑\\n\\nChange the Y value to adjust how much the **spine** should rotate based on head rotation.\""},"Content":{"type":"string","value":"\"↑↑↑↑↑↑↑↑\\n\\nChange the Y value to adjust how much the **spine** should rotate based on head rotation.\""},"Editing":{"type":"bool","value":"false"}},"typeId":"200ee639-79bc-492c-a14c-a6b64cfcf39d","name":"COMMENT","x":301.85437,"y":636.8304},"fa732928-86fe-46a5-88af-603a1c9b0732":{"id":"fa732928-86fe-46a5-88af-603a1c9b0732","dataInputs":{"Text":{"type":"string","value":"\"↑↑↑↑↑↑↑↑\\n\\nChange the Y value to adjust how much the **hips** should rotate based on head rotation.\""},"Content":{"type":"string","value":"\"↑↑↑↑↑↑↑↑\\n\\nChange the Y value to adjust how much the **hips** should rotate based on head rotation.\""},"Editing":{"type":"bool","value":"false"}},"typeId":"200ee639-79bc-492c-a14c-a6b64cfcf39d","name":"COMMENT","x":657.979858,"y":639.964233},"5316a549-0d20-493a-bc13-71778171cece":{"id":"5316a549-0d20-493a-bc13-71778171cece","dataInputs":{"FunctionName":{"type":"string","value":"\"SetUpperBodyRotationSettings\""},"Parameters":{"type":"Warudo.Plugins.Core.Nodes.ParameterData[]","value":"[{\"id\":\"68a26fcf-dc2e-4fe6-961d-21986aba76b3\",\"dataInputs\":{\"ParameterName\":{\"type\":\"string\",\"value\":\"\\\"chestRotation\\\"\"},\"ParameterType\":{\"type\":\"string\",\"value\":\"\\\"float\\\"\"}}},{\"id\":\"0e181f0a-06c3-46a2-af06-d70eb78a16b9\",\"dataInputs\":{\"ParameterName\":{\"type\":\"string\",\"value\":\"\\\"spineRotation\\\"\"},\"ParameterType\":{\"type\":\"string\",\"value\":\"\\\"float\\\"\"}}},{\"id\":\"c9e29289-11fb-417e-9c02-974cbb6d4fae\",\"dataInputs\":{\"ParameterName\":{\"type\":\"string\",\"value\":\"\\\"hipRotation\\\"\"},\"ParameterType\":{\"type\":\"string\",\"value\":\"\\\"float\\\"\"}}}]"},"ResultType":{"type":"string","value":null}},"typeId":"c240b67e-8891-48a2-a56c-506aa5ecaa18","name":"DEFINE_FUNCTION","x":-995.790833,"y":1104.65808},"b8c3699c-21a4-4dc2-a08f-84cc43464342":{"id":"b8c3699c-21a4-4dc2-a08f-84cc43464342","dataInputs":{"X":{"type":"float","value":"0.0"},"Y":{"type":"float","value":"0.6"},"Z":{"type":"float","value":"0.0"}},"typeId":"fafc477f-cd4a-44da-8b9d-27f2e66fc255","name":"VECTOR3","x":-395.537872,"y":1102.75427},"3dd66d0c-b1a6-43a2-bc54-1b02e5cfdf37":{"id":"3dd66d0c-b1a6-43a2-bc54-1b02e5cfdf37","dataInputs":{"TargetGraph":{"type":"string","value":null},"VariableName":{"type":"string","value":"\"debug\""},"Value":{"type":"float","value":"1.30000007"}},"typeId":"d2ceb9ff-ecca-4858-a0b0-ab945b204df4","name":"SET_FLOAT_VARIABLE","x":204.330276,"y":1102.99182},"2cc85cd9-9269-4c55-8047-6b5d317c396b":{"id":"2cc85cd9-9269-4c55-8047-6b5d317c396b","dataInputs":{"MathExpression":{"type":"string","value":"\"a+b+c\""},"CompilationError":{"type":"string","value":null},"a":{"type":"float","value":"0.6"},"b":{"type":"float","value":"0.4"},"c":{"type":"float","value":"0.3"}},"typeId":"9bd3c051-1a02-4e35-b3d3-bea3b3a3150e","name":"MATH_EXPRESSION","x":-97.25906,"y":1203.71716},"74cad2e2-1be8-4eed-a2a7-3575b2141468":{"id":"74cad2e2-1be8-4eed-a2a7-3575b2141468","dataInputs":{"Text":{"type":"string","value":"\"Hip Rotation\""},"Content":{"type":"string","value":"\"Hip Rotation\""},"Editing":{"type":"bool","value":"false"}},"typeId":"200ee639-79bc-492c-a14c-a6b64cfcf39d","name":"COMMENT","x":1003.76184,"y":703.3677},"8624133b-85da-4ab1-8fa4-5af18ac1f95f":{"id":"8624133b-85da-4ab1-8fa4-5af18ac1f95f","dataInputs":{"Text":{"type":"string","value":"\"Spine Rotation\""},"Content":{"type":"string","value":"\"Spine Rotation\""},"Editing":{"type":"bool","value":"false"}},"typeId":"200ee639-79bc-492c-a14c-a6b64cfcf39d","name":"COMMENT","x":1002.90674,"y":503.089661},"bc26c5bc-aa90-441f-87e6-e6a8ab4c3250":{"id":"bc26c5bc-aa90-441f-87e6-e6a8ab4c3250","dataInputs":{"Text":{"type":"string","value":"\"Chest Rotation\""},"Content":{"type":"string","value":"\"Chest Rotation\""},"Editing":{"type":"bool","value":"false"}},"typeId":"200ee639-79bc-492c-a14c-a6b64cfcf39d","name":"COMMENT","x":1002.95093,"y":303.782928},"d5885114-3e18-4f43-b098-4f0e2cf9a33b":{"id":"d5885114-3e18-4f43-b098-4f0e2cf9a33b","dataInputs":{"X":{"type":"float","value":"0.0"},"Y":{"type":"float","value":"0.4"},"Z":{"type":"float","value":"0.0"}},"typeId":"fafc477f-cd4a-44da-8b9d-27f2e66fc255","name":"VECTOR3","x":-393.5869,"y":1408.856},"3fb6744a-3ddd-4d7b-9391-ecbe2faa70a0":{"id":"3fb6744a-3ddd-4d7b-9391-ecbe2faa70a0","dataInputs":{"X":{"type":"float","value":"0.0"},"Y":{"type":"float","value":"0.3"},"Z":{"type":"float","value":"0.0"}},"typeId":"fafc477f-cd4a-44da-8b9d-27f2e66fc255","name":"VECTOR3","x":-393.5869,"y":1711.97327},"f1e15600-e9d7-424e-99dd-7df3b082fec3":{"id":"f1e15600-e9d7-424e-99dd-7df3b082fec3","dataInputs":{"Value":{"type":"float","value":"0.6"}},"typeId":"649e3776-566f-4a9e-a3c7-63d4cfacdc90","name":"FLOAT","x":-697.5715,"y":1203.62},"a33de1b6-a17c-40c8-92a8-d333d3b8f117":{"id":"a33de1b6-a17c-40c8-92a8-d333d3b8f117","dataInputs":{"Value":{"type":"float","value":"0.4"}},"typeId":"649e3776-566f-4a9e-a3c7-63d4cfacdc90","name":"FLOAT","x":-697.063354,"y":1503.5509},"5a031451-20ac-4f84-95fd-5b4b33e197b8":{"id":"5a031451-20ac-4f84-95fd-5b4b33e197b8","dataInputs":{"Value":{"type":"float","value":"0.3"}},"typeId":"649e3776-566f-4a9e-a3c7-63d4cfacdc90","name":"FLOAT","x":-697.0629,"y":1803.09265},"dd640d39-9d4e-4ac0-ba6e-89aee8bb389b":{"id":"dd640d39-9d4e-4ac0-ba6e-89aee8bb389b","dataInputs":{"Text":{"type":"string","value":"\"I don't know why, and at this point I don't care.\\n\\nBut if you remove this \\\"Math Expression\\\" and \\\"Set Float Variable\\\", you wouldn't be able to update the settings from the control panel.\""},"Content":{"type":"string","value":"\"I don't know why, and at this point I don't care.\\n\\nBut if you remove this \\\"Math Expression\\\" and \\\"Set Float Variable\\\", you wouldn't be able to update the settings from the control panel.\""},"Editing":{"type":"bool","value":"false"}},"typeId":"200ee639-79bc-492c-a14c-a6b64cfcf39d","name":"COMMENT","x":202.843933,"y":1503.60461},"8522a12a-c545-4347-a5a4-2db686e46005":{"id":"8522a12a-c545-4347-a5a4-2db686e46005","dataInputs":{"Text":{"type":"string","value":"\"# Read Me\\nThis extra bit that allows you to change the settings via my control panel is what I added. I honestly have no idea if it'll import correctly.\\n\\n-CMDR Phoenix\""},"Content":{"type":"string","value":"\"# Read Me\\nThis extra bit that allows you to change the settings via my control panel is what I added. I honestly have no idea if it'll import correctly.\\n\\n-CMDR Phoenix\""},"Editing":{"type":"bool","value":"false"}},"typeId":"200ee639-79bc-492c-a14c-a6b64cfcf39d","name":"COMMENT","x":-1296.16626,"y":1103.14893},"e8186457-bcd9-48d1-a380-4bd1defce038":{"id":"e8186457-bcd9-48d1-a380-4bd1defce038","dataInputs":{"Text":{"type":"string","value":"\"# Read Me\\nThis blueprint is technically required to use with my Natural Body Movement / Tilt\\n\\n-CMDR Phoenix\""},"Content":{"type":"string","value":"\"# Read Me\\nThis blueprint is technically required to use with my Natural Body Movement / Tilt\\n\\n-CMDR Phoenix\""},"Editing":{"type":"bool","value":"false"}},"typeId":"200ee639-79bc-492c-a14c-a6b64cfcf39d","name":"COMMENT","x":1303.54626,"y":103.14875}},"dataConnections":[{"outputNode":"26500fe5-1342-46b9-b3ac-200daaa34bdf","inputNode":"4ff5a3d9-fab4-4460-82e5-d10fa4309a29","outputPort":"OutputRotations","inputPort":"BoneRotationOffsets"},{"outputNode":"eea1cbc8-f7f6-49be-8ecf-127db682d90b","inputNode":"6728c52d-c7b2-4848-b5aa-1c3a5209b65e","outputPort":"OutputRotations","inputPort":"Rotations"},{"outputNode":"7be9914f-70cf-4450-b15c-5d75658ae714","inputNode":"6728c52d-c7b2-4848-b5aa-1c3a5209b65e","outputPort":"OutputVector3","inputPort":"OffsetEulerAngle"},{"outputNode":"372dcb2a-01ce-4d69-ba7a-365187c62217","inputNode":"eea1cbc8-f7f6-49be-8ecf-127db682d90b","outputPort":"BoneRotationOffsets","inputPort":"Rotations"},{"outputNode":"58321c17-cd8e-4868-8f19-da8f940ca059","inputNode":"eea1cbc8-f7f6-49be-8ecf-127db682d90b","outputPort":"OutputVector3","inputPort":"OffsetEulerAngle"},{"outputNode":"6728c52d-c7b2-4848-b5aa-1c3a5209b65e","inputNode":"26500fe5-1342-46b9-b3ac-200daaa34bdf","outputPort":"OutputRotations","inputPort":"Rotations"},{"outputNode":"5bbb8b57-9d79-465e-9e94-6be043e5f9fb","inputNode":"26500fe5-1342-46b9-b3ac-200daaa34bdf","outputPort":"OutputVector3","inputPort":"OffsetEulerAngle"},{"outputNode":"717cb3d7-58f2-4af2-ab6c-1fccb6b39585","inputNode":"58321c17-cd8e-4868-8f19-da8f940ca059","outputPort":"BoneRotationEulerAngles","inputPort":"Scale"},{"outputNode":"b8c3699c-21a4-4dc2-a08f-84cc43464342","inputNode":"58321c17-cd8e-4868-8f19-da8f940ca059","outputPort":"Output","inputPort":"Vector3"},{"outputNode":"717cb3d7-58f2-4af2-ab6c-1fccb6b39585","inputNode":"7be9914f-70cf-4450-b15c-5d75658ae714","outputPort":"BoneRotationEulerAngles","inputPort":"Scale"},{"outputNode":"d5885114-3e18-4f43-b098-4f0e2cf9a33b","inputNode":"7be9914f-70cf-4450-b15c-5d75658ae714","outputPort":"Output","inputPort":"Vector3"},{"outputNode":"717cb3d7-58f2-4af2-ab6c-1fccb6b39585","inputNode":"5bbb8b57-9d79-465e-9e94-6be043e5f9fb","outputPort":"BoneRotationEulerAngles","inputPort":"Scale"},{"outputNode":"3fb6744a-3ddd-4d7b-9391-ecbe2faa70a0","inputNode":"5bbb8b57-9d79-465e-9e94-6be043e5f9fb","outputPort":"Output","inputPort":"Vector3"},{"outputNode":"2cc85cd9-9269-4c55-8047-6b5d317c396b","inputNode":"3dd66d0c-b1a6-43a2-bc54-1b02e5cfdf37","outputPort":"OutputFloat","inputPort":"Value"},{"outputNode":"f1e15600-e9d7-424e-99dd-7df3b082fec3","inputNode":"b8c3699c-21a4-4dc2-a08f-84cc43464342","outputPort":"Output","inputPort":"Y"},{"outputNode":"a33de1b6-a17c-40c8-92a8-d333d3b8f117","inputNode":"d5885114-3e18-4f43-b098-4f0e2cf9a33b","outputPort":"Output","inputPort":"Y"},{"outputNode":"5a031451-20ac-4f84-95fd-5b4b33e197b8","inputNode":"3fb6744a-3ddd-4d7b-9391-ecbe2faa70a0","outputPort":"Output","inputPort":"Y"},{"outputNode":"5316a549-0d20-493a-bc13-71778171cece","inputNode":"5a031451-20ac-4f84-95fd-5b4b33e197b8","outputPort":"Parameter_2","inputPort":"Value"},{"outputNode":"5316a549-0d20-493a-bc13-71778171cece","inputNode":"a33de1b6-a17c-40c8-92a8-d333d3b8f117","outputPort":"Parameter_1","inputPort":"Value"},{"outputNode":"5316a549-0d20-493a-bc13-71778171cece","inputNode":"f1e15600-e9d7-424e-99dd-7df3b082fec3","outputPort":"Parameter_0","inputPort":"Value"},{"outputNode":"5a031451-20ac-4f84-95fd-5b4b33e197b8","inputNode":"2cc85cd9-9269-4c55-8047-6b5d317c396b","outputPort":"Output","inputPort":"c"},{"outputNode":"a33de1b6-a17c-40c8-92a8-d333d3b8f117","inputNode":"2cc85cd9-9269-4c55-8047-6b5d317c396b","outputPort":"Output","inputPort":"b"},{"outputNode":"f1e15600-e9d7-424e-99dd-7df3b082fec3","inputNode":"2cc85cd9-9269-4c55-8047-6b5d317c396b","outputPort":"Output","inputPort":"a"}],"flowConnections":[{"outputNode":"2d7d151c-cdf9-46d0-b0ae-6826e617542f","inputNode":"4ff5a3d9-fab4-4460-82e5-d10fa4309a29","outputPort":"Exit","inputPort":"Enter"},{"outputNode":"5316a549-0d20-493a-bc13-71778171cece","inputNode":"3dd66d0c-b1a6-43a2-bc54-1b02e5cfdf37","outputPort":"OnInvoke","inputPort":"Enter"}],"properties":{"id":"70faa2dc-836a-45e6-a13e-66ef3589c850","dataInputs":{"Variables":{"type":"Warudo.Core.Graphs.GraphVariable[]","value":"[{\"id\":\"62a6c20b-b9f6-44bc-8cca-09dbf0e53625\",\"dataInputs\":{\"Name\":{\"type\":\"string\",\"value\":\"\\\"debug\\\"\"},\"DuplicateNameWarning\":{\"type\":\"string\",\"value\":\"\\\"**A variable with this name already exists.**\\\"\"},\"VariableType\":{\"type\":\"Warudo.Core.Graphs.GraphVariableType\",\"value\":\"{\\\"label\\\":\\\"Float\\\",\\\"value\\\":2,\\\"description\\\":null,\\\"icon\\\":null}\"},\"BooleanValue\":{\"type\":\"bool\",\"value\":\"false\"},\"IntegerValue\":{\"type\":\"int\",\"value\":\"0\"},\"FloatValue\":{\"type\":\"float\",\"value\":\"0.0\"},\"StringValue\":{\"type\":\"string\",\"value\":null},\"Vector3Value\":{\"type\":\"UnityEngine.Vector3\",\"value\":\"{\\\"x\\\":0.0,\\\"y\\\":0.0,\\\"z\\\":0.0}\"},\"BooleanListValue\":{\"type\":\"bool[]\",\"value\":\"[]\"},\"IntegerListValue\":{\"type\":\"int[]\",\"value\":\"[]\"},\"FloatListValue\":{\"type\":\"float[]\",\"value\":\"[]\"},\"StringListValue\":{\"type\":\"string[]\",\"value\":\"[]\"},\"Vector3ListValue\":{\"type\":\"UnityEngine.Vector3[]\",\"value\":\"[]\"}}}]"}}}}